codeconcat/__init__.py
codeconcat/cli.py
codeconcat/config.py
codeconcat/file_utils.py
codeconcat/main.py
codeconcat/output.py
codeconcat-2.2.2.dist-info/licenses/LICENSE
codeconcat-2.2.2.dist-info/METADATA
codeconcat-2.2.2.dist-info/WHEEL
codeconcat-2.2.2.dist-info/entry_points.txt
codeconcat-2.2.2.dist-info/top_level.txt
codeconcat-2.2.2.dist-info/RECORD
