Metadata-Version: 2.4
Name: codeconcat
Version: 2.2.2
Summary: A tool to concatenate folders into a single text file, respecting .gitignore and using optional config.
Author-email: Luis Guilherme <lgpelin92@gmail.com>
License: MIT License
Project-URL: Homepage, https://github.com/lguibr/CodeConcat
Project-URL: Bug Tracker, https://github.com/lguibr/CodeConcat/issues
Project-URL: Source Code, https://github.com/lguibr/CodeConcat
Keywords: concatenate,code,llm,context,cli,tool,gitignore,config
Classifier: Development Status :: 3 - Alpha
Classifier: Intended Audience :: Developers
Classifier: License :: OSI Approved :: MIT License
Classifier: Operating System :: OS Independent
Classifier: Programming Language :: Python :: 3
Classifier: Programming Language :: Python :: 3.7
Classifier: Programming Language :: Python :: 3.8
Classifier: Programming Language :: Python :: 3.9
Classifier: Programming Language :: Python :: 3.10
Classifier: Programming Language :: Python :: 3.11
Classifier: Programming Language :: Python :: 3.12
Classifier: Topic :: Software Development :: Libraries :: Python Modules
Classifier: Topic :: Text Processing
Classifier: Topic :: Utilities
Requires-Python: >=3.7
License-File: LICENSE
Requires-Dist: python-magic
Requires-Dist: pathspec>=0.11
Provides-Extra: test
Requires-Dist: ruff; extra == "test"
Requires-Dist: mypy>=1.0; extra == "test"
Requires-Dist: types-setuptools; extra == "test"
Requires-Dist: pytest>=7.0; extra == "test"
Dynamic: license-file
